{"commitInfo":{"timestamp":1750077565114,"userId":"4833629471493945","userName":"azuser3545_mml.local@techademy.com","operation":"WRITE","operationParameters":{"mode":"Overwrite","statsOnLoad":false,"partitionBy":"[]"},"notebook":{"notebookId":"1264760716287568"},"clusterId":"0611-043339-3vb7b9iv","readVersion":6,"isolationLevel":"WriteSerializable","isBlindAppend":false,"operationMetrics":{"numFiles":"1","numOutputRows":"4","numOutputBytes":"1627"},"tags":{"noRowsCopied":"true","restoresDeletedRows":"false"},"engineInfo":"Databricks-Runtime/15.4.x-photon-scala2.12","txnId":"ebcefba0-1c6f-4c15-b564-a8832495ecf0"}}
{"add":{"path":"part-00000-0fdc44a7-faf9-4c45-8e09-92d488d314eb.c000.snappy.parquet","partitionValues":{},"size":1627,"modificationTime":1750077564939,"dataChange":true,"stats":"{\"numRecords\":4,\"minValues\":{\"ProductID\":\"P1001\",\"ProductName\":\"Keyboard\",\"Category\":\"Accessories\",\"Stock\":5,\"ReorderLevel\":2.0},\"maxValues\":{\"ProductID\":\"P1004\",\"ProductName\":\"Tablet\",\"Category\":\"Electronics\",\"Stock\":15,\"ReorderLevel\":5.0},\"nullCount\":{\"ProductID\":0,\"ProductName\":0,\"Category\":0,\"Stock\":0,\"ReorderLevel\":0},\"tightBounds\":true}","tags":{"INSERTION_TIME":"1750077564939000","MIN_INSERTION_TIME":"1750077564939000","MAX_INSERTION_TIME":"1750077564939000","OPTIMIZE_TARGET_SIZE":"268435456"}}}
{"remove":{"path":"part-00000-1fa93709-7719-4109-9064-9bafe2ff0bb5.c000.snappy.parquet","deletionTimestamp":1750077565113,"dataChange":true,"extendedFileMetadata":true,"partitionValues":{},"size":1627,"tags":{"INSERTION_TIME":"1750077427633000","MIN_INSERTION_TIME":"1750077427633000","MAX_INSERTION_TIME":"1750077427633000","OPTIMIZE_TARGET_SIZE":"268435456"}}}
